klotski/README.md
klotski/__init__.py
klotski/__main__.py
klotski/boards.kts
klotski/kl_board.py
klotski/kl_board_chooser.py
klotski/kl_enum.py
klotski/kl_map.py
klotski/klotski-icon.png
klotski/klotski-tiles.png
klotski/klotski.py
Klotski-1.3.2.dist-info/LICENSE.txt
Klotski-1.3.2.dist-info/METADATA
Klotski-1.3.2.dist-info/WHEEL
Klotski-1.3.2.dist-info/entry_points.txt
Klotski-1.3.2.dist-info/top_level.txt
Klotski-1.3.2.dist-info/RECORD
