Metadata-Version: 2.1
Name: Klotski
Version: 1.3.2
Summary: A brain-teaser game
Home-page: https://github.com/bluebird75/klotski
Author: Philippe Fremy
Author-email: phil.fremy@free.fr
License: GNU GPL
Project-URL: Source, https://github.com/bluebird75/klotski/
Project-URL: Tracker, https://github.com/bluebird75/klotski/issues
Keywords: game
Platform: UNKNOWN
Classifier: Development Status :: 5 - Production/Stable
Classifier: License :: OSI Approved :: GNU General Public License v2 or later (GPLv2+)
Classifier: Operating System :: MacOS
Classifier: Operating System :: Microsoft :: Windows
Classifier: Operating System :: POSIX
Classifier: Programming Language :: Python :: 3 :: Only
Classifier: Programming Language :: Python :: Implementation :: CPython
Classifier: Topic :: Education
Classifier: Topic :: Games/Entertainment :: Board Games
Classifier: Intended Audience :: Education
Classifier: Natural Language :: English
Requires-Python: >=3.5
License-File: LICENSE.txt
Requires-Dist: PyQt5 (>=5.6)
Requires-Dist: sip (>=4.18)
